CHANGELOG.rst
LICENCE
django_any_js/__init__.py
django_any_js/apps.py
django_any_js/templates/django_any_js/css.html
django_any_js/templates/django_any_js/js.html
django_any_js/templatetags/__init__.py
django_any_js/templatetags/any_js.py
django_any_js-1.2.dist-info/METADATA
django_any_js-1.2.dist-info/WHEEL
django_any_js-1.2.dist-info/RECORD
