Metadata-Version: 2.1
Name: django-any-js
Version: 1.2
Summary: Include JavaScript/CSS libraries with readable template tags
Home-page: https://edugit.org/AlekSIS/libs/django-any-js
License: Apache-2.0
Author: Dominik George
Author-email: dominik.george@teckids.org
Maintainer: Dominik George
Maintainer-email: dominik.george@teckids.org
Requires-Python: >=3.10,<4.0
Classifier: Environment :: Web Environment
Classifier: Framework :: Django
Classifier: Framework :: Django :: 2.2
Classifier: Framework :: Django :: 3.0
Classifier: Framework :: Django :: 3.1
Classifier: Framework :: Django :: 3.2
Classifier: License :: OSI Approved :: Apache Software License
Classifier: Operating System :: OS Independent
Classifier: Programming Language :: Python
Classifier: Programming Language :: Python :: 3
Classifier: Programming Language :: Python :: 3.10
Classifier: Programming Language :: Python :: 3.11
Classifier: Topic :: Internet :: WWW/HTTP
Classifier: Topic :: Internet :: WWW/HTTP :: Dynamic Content
Requires-Dist: Django (>=4.2,<6.0)
Project-URL: Repository, https://edugit.org/AlekSIS/libs/django-any-js
